hyperpocket_openai/__init__.py
hyperpocket_openai/pocket_openai.py
hyperpocket_openai/util/__init__.py
hyperpocket_openai/util/tool_to_open_ai_spec.py
hyperpocket_openai-0.5.7.dist-info/METADATA
hyperpocket_openai-0.5.7.dist-info/WHEEL
hyperpocket_openai-0.5.7.dist-info/RECORD
