Metadata-Version: 2.4
Name: hyperpocket-openai
Version: 0.5.7
Author-email: Hyperpocket Team <hyperpocket@vessl.ai>
Requires-Python: >=3.10
Requires-Dist: hyperpocket>=0.0.3
Requires-Dist: openai-agents>=0.0.3
Requires-Dist: openai>=1.7.0
